[
  {
    "date": "2026-01-05 14:46:36",
    "referenceCode": "407B45",
    "email": "mbnk7agf0o@airsworld.net",
    "username": "gamer8439",
    "password": "2v%8gUTU",
    "age": 19,
    "gender": "masculino",
    "inviteCodeUsed": "6247C5",
    "emailVerified": true
  },
  {
    "date": "2026-01-05 14:48:09",
    "referenceCode": "603897",
    "email": "40ktk4sikh@airsworld.net",
    "username": "ultra4253",
    "password": "1nDxhX%z",
    "age": 23,
    "gender": "masculino",
    "inviteCodeUsed": "6247C5",
    "emailVerified": true
  },
  {
    "date": "2026-01-05 14:51:38",
    "referenceCode": "A51155",
    "email": "xdkyn59flv@airsworld.net",
    "username": "pro0303",
    "password": "h8I4#eOY",
    "age": 29,
    "gender": "feminino",
    "inviteCodeUsed": "6247C5",
    "emailVerified": true
  },
  {
    "date": "2026-01-05 14:52:26",
    "referenceCode": "D2E7DE",
    "email": "olb731pc3m@airsworld.net",
    "username": "gamer7526",
    "password": "Bl1OWe!O",
    "age": 23,
    "gender": "masculino",
    "inviteCodeUsed": "6247C5",
    "emailVerified": true
  },
  {
    "date": "2026-01-05 14:59:39",
    "referenceCode": "5A054A",
    "email": "25w5b291wa@airsworld.net",
    "username": "pro6483",
    "password": "dcV%8ji0",
    "age": 33,
    "gender": "feminino",
    "inviteCodeUsed": "6247C5",
    "emailVerified": true
  },
  {
    "date": "2026-01-05 17:07:01",
    "referenceCode": "A76C80",
    "email": "qjt216a3w2@airsworld.net",
    "username": "player2900",
    "password": "Db27unx&",
    "age": 36,
    "gender": "feminino",
    "inviteCodeUsed": "6247C5",
    "emailVerified": true
  },
  {
    "date": "2026-01-05 17:08:02",
    "referenceCode": "BDB2CF",
    "email": "igm38ku62z@airsworld.net",
    "username": "player1619",
    "password": "B$006nFj",
    "age": 34,
    "gender": "masculino",
    "inviteCodeUsed": "6247C5",
    "emailVerified": true
  },
  {
    "date": "2026-01-05 17:23:34",
    "referenceCode": "13E3B8",
    "email": "i2lcz8td0w@airsworld.net",
    "username": "max6826",
    "password": "Xv5R5#Rv",
    "age": 22,
    "gender": "feminino",
    "inviteCodeUsed": "6247C5",
    "emailVerified": true
  },
  {
    "date": "2026-01-05 17:24:01",
    "referenceCode": "75292A",
    "email": "b2blkbsont@airsworld.net",
    "username": "mega0864",
    "password": "P1B4zXy@",
    "age": 21,
    "gender": "masculino",
    "inviteCodeUsed": "6247C5",
    "emailVerified": true
  },
  {
    "date": "2026-01-05 17:24:19",
    "referenceCode": "F8DBD2",
    "email": "i5cdct1ptg@airsworld.net",
    "username": "star9193",
    "password": "5V@R0Muh",
    "age": 36,
    "gender": "masculino",
    "inviteCodeUsed": "6247C5",
    "emailVerified": true
  },
  {
    "date": "2026-01-05 17:26:50",
    "referenceCode": "C994ED",
    "email": "v95nksn12w@airsworld.net",
    "username": "cool0274",
    "password": "rN&z27Ca",
    "age": 31,
    "gender": "masculino",
    "inviteCodeUsed": "6247C5",
    "emailVerified": true
  },
  {
    "date": "2026-01-05 17:27:14",
    "referenceCode": "39A825",
    "email": "b61cbv45a7@airsworld.net",
    "username": "ultra4054",
    "password": "J7KC1!wR",
    "age": 41,
    "gender": "feminino",
    "inviteCodeUsed": "6247C5",
    "emailVerified": true
  },
  {
    "date": "2026-01-05 17:27:51",
    "referenceCode": "F79012",
    "email": "v0vo0gydvi@airsworld.net",
    "username": "mega4956",
    "password": "JDoaO!l6",
    "age": 25,
    "gender": "masculino",
    "inviteCodeUsed": "6247C5",
    "emailVerified": true
  },
  {
    "date": "2026-01-05 18:14:29",
    "referenceCode": "057CF7",
    "email": "ck7w159ygs@airsworld.net",
    "username": "NovaMaster29",
    "password": "1s9x22UMw7mk",
    "age": 32,
    "gender": "feminino",
    "inviteCodeUsed": "6247C5",
    "emailVerified": true
  },
  {
    "date": "2026-01-05 18:14:46",
    "referenceCode": "F00BB4",
    "email": "8hcbkrykuj@airsworld.net",
    "username": "SuperStar0596",
    "password": "D64AgKR7rAlU",
    "age": 40,
    "gender": "feminino",
    "inviteCodeUsed": "6247C5",
    "emailVerified": true
  },
  {
    "date": "2026-01-05 18:15:05",
    "referenceCode": "A5828B",
    "email": "smyet8dpuh@airsworld.net",
    "username": "ProKing719",
    "password": "UYhqIjLYMSp7",
    "age": 43,
    "gender": "feminino",
    "inviteCodeUsed": "6247C5",
    "emailVerified": true
  },
  {
    "date": "2026-01-05 18:15:24",
    "referenceCode": "9289CD",
    "email": "ssoci6wsxa@airsworld.net",
    "username": "UltraPro8380",
    "password": "jOToTxT8M2%N",
    "age": 34,
    "gender": "masculino",
    "inviteCodeUsed": "6247C5",
    "emailVerified": true
  },
  {
    "date": "2026-01-05 18:15:41",
    "referenceCode": "AD1DAF",
    "email": "7neu3ev7wi@airsworld.net",
    "username": "UltraPro17",
    "password": "F2aeFHFLVTi$",
    "age": 43,
    "gender": "feminino",
    "inviteCodeUsed": "6247C5",
    "emailVerified": true
  },
  {
    "date": "2026-01-05 18:15:58",
    "referenceCode": "2DBEA0",
    "email": "02g7h5mzmt@airsworld.net",
    "username": "CoolLegend589",
    "password": "TJg8rdyvLqvW",
    "age": 36,
    "gender": "masculino",
    "inviteCodeUsed": "6247C5",
    "emailVerified": true
  },
  {
    "date": "2026-01-05 18:16:16",
    "referenceCode": "721924",
    "email": "3ne8j2n5ws@airsworld.net",
    "username": "EpicKing7870",
    "password": "Ne!234QRs1hO",
    "age": 32,
    "gender": "masculino",
    "inviteCodeUsed": "6247C5",
    "emailVerified": true
  },
  {
    "date": "2026-01-05 18:16:34",
    "referenceCode": "CCC3B7",
    "email": "6eb0177shh@airsworld.net",
    "username": "PlayLord95",
    "password": "9Csv5AJ0nDPV",
    "age": 36,
    "gender": "feminino",
    "inviteCodeUsed": "6247C5",
    "emailVerified": true
  },
  {
    "date": "2026-01-05 18:16:52",
    "referenceCode": "92B58E",
    "email": "t7yyjp7ler@airsworld.net",
    "username": "SuperLord31",
    "password": "NJQkHhPJqmQf",
    "age": 44,
    "gender": "masculino",
    "inviteCodeUsed": "6247C5",
    "emailVerified": true
  },
  {
    "date": "2026-01-05 18:17:09",
    "referenceCode": "E4E406",
    "email": "j4r757ut75@airsworld.net",
    "username": "SuperHero41",
    "password": "cQPJCYqraTpD",
    "age": 25,
    "gender": "feminino",
    "inviteCodeUsed": "6247C5",
    "emailVerified": true
  },
  {
    "date": "2026-01-05 18:17:25",
    "referenceCode": "26913D",
    "email": "byubk0kdiy@airsworld.net",
    "username": "SuperLegend7109",
    "password": "bqadOWHsj5gH",
    "age": 35,
    "gender": "feminino",
    "inviteCodeUsed": "6247C5",
    "emailVerified": true
  },
  {
    "date": "2026-01-05 18:17:42",
    "referenceCode": "5BB359",
    "email": "xlse8y0bml@airsworld.net",
    "username": "MegaStar118",
    "password": "n5ehiOTeH%oV",
    "age": 18,
    "gender": "masculino",
    "inviteCodeUsed": "6247C5",
    "emailVerified": true
  },
  {
    "date": "2026-01-05 18:18:00",
    "referenceCode": "ABC475",
    "email": "abf8kavz7q@airsworld.net",
    "username": "SuperStar733",
    "password": "xIuMqKAwZfNC",
    "age": 23,
    "gender": "masculino",
    "inviteCodeUsed": "6247C5",
    "emailVerified": true
  },
  {
    "date": "2026-01-05 18:18:17",
    "referenceCode": "B511B9",
    "email": "yyq2on3aou@airsworld.net",
    "username": "NovaPro2097",
    "password": "kj2$P@J8Wy3E",
    "age": 26,
    "gender": "feminino",
    "inviteCodeUsed": "6247C5",
    "emailVerified": true
  },
  {
    "date": "2026-01-05 18:18:35",
    "referenceCode": "F6F1A6",
    "email": "zkv2ezpqif@airsworld.net",
    "username": "StarKing730",
    "password": "#jw20TJFmuYK",
    "age": 18,
    "gender": "masculino",
    "inviteCodeUsed": "6247C5",
    "emailVerified": true
  },
  {
    "date": "2026-01-05 18:18:51",
    "referenceCode": "1955E5",
    "email": "jqlr3um589@airsworld.net",
    "username": "GameMaster077",
    "password": "7HKYsF$7J7lW",
    "age": 36,
    "gender": "feminino",
    "inviteCodeUsed": "6247C5",
    "emailVerified": true
  },
  {
    "date": "2026-01-05 18:19:09",
    "referenceCode": "4B3A9C",
    "email": "rh7zzuru2j@airsworld.net",
    "username": "StarStar99",
    "password": "IjBAhIZl!cHn",
    "age": 29,
    "gender": "feminino",
    "inviteCodeUsed": "6247C5",
    "emailVerified": true
  },
  {
    "date": "2026-01-05 18:19:25",
    "referenceCode": "F84BF7",
    "email": "e40vu2or73@airsworld.net",
    "username": "CoolKing9959",
    "password": "g3eCsCr39Gxy",
    "age": 18,
    "gender": "feminino",
    "inviteCodeUsed": "6247C5",
    "emailVerified": true
  },
  {
    "date": "2026-01-05 18:19:41",
    "referenceCode": "E51538",
    "email": "i8yeve5e5j@airsworld.net",
    "username": "MegaGamer6234",
    "password": "TuIm4%N8tMcy",
    "age": 41,
    "gender": "masculino",
    "inviteCodeUsed": "6247C5",
    "emailVerified": true
  },
  {
    "date": "2026-01-05 18:19:58",
    "referenceCode": "313852",
    "email": "jj9f9lndxv@airsworld.net",
    "username": "SuperStar429",
    "password": "Tv6JbarA8w#A",
    "age": 30,
    "gender": "masculino",
    "inviteCodeUsed": "6247C5",
    "emailVerified": true
  },
  {
    "date": "2026-01-05 18:20:15",
    "referenceCode": "324E7D",
    "email": "wimly744bp@airsworld.net",
    "username": "NovaGamer185",
    "password": "eP0Dm79EibSG",
    "age": 20,
    "gender": "masculino",
    "inviteCodeUsed": "6247C5",
    "emailVerified": true
  },
  {
    "date": "2026-01-05 18:20:32",
    "referenceCode": "B204B1",
    "email": "z6wxay4ig5@airsworld.net",
    "username": "NovaMaster841",
    "password": "KflzfmCgVdjL",
    "age": 42,
    "gender": "feminino",
    "inviteCodeUsed": "6247C5",
    "emailVerified": true
  },
  {
    "date": "2026-01-05 18:20:49",
    "referenceCode": "A54720",
    "email": "yutiym5kws@airsworld.net",
    "username": "PlayHero4176",
    "password": "dQJFYW$VjIiT",
    "age": 42,
    "gender": "masculino",
    "inviteCodeUsed": "6247C5",
    "emailVerified": true
  },
  {
    "date": "2026-01-05 18:21:06",
    "referenceCode": "F534F4",
    "email": "syir8za4yy@airsworld.net",
    "username": "EpicKing216",
    "password": "Mr%curcvsWk6",
    "age": 26,
    "gender": "masculino",
    "inviteCodeUsed": "6247C5",
    "emailVerified": true
  },
  {
    "date": "2026-01-05 18:21:24",
    "referenceCode": "6DD3F5",
    "email": "28xri978ha@airsworld.net",
    "username": "CoolMaster50",
    "password": "8y8c@iE@lSUS",
    "age": 42,
    "gender": "masculino",
    "inviteCodeUsed": "6247C5",
    "emailVerified": true
  },
  {
    "date": "2026-01-05 18:21:40",
    "referenceCode": "B808E5",
    "email": "e7gltrwkrf@airsworld.net",
    "username": "UltraStar17",
    "password": "$6%#afuratq4",
    "age": 29,
    "gender": "feminino",
    "inviteCodeUsed": "6247C5",
    "emailVerified": true
  },
  {
    "date": "2026-01-05 18:21:57",
    "referenceCode": "23CAD1",
    "email": "tjsmloqhqm@airsworld.net",
    "username": "SuperLegend26",
    "password": "YnPhwk7LnD5j",
    "age": 34,
    "gender": "masculino",
    "inviteCodeUsed": "6247C5",
    "emailVerified": true
  },
  {
    "date": "2026-01-05 18:22:13",
    "referenceCode": "F349A9",
    "email": "st5afi0djb@airsworld.net",
    "username": "MegaKing399",
    "password": "xmj@##QL0DC#",
    "age": 28,
    "gender": "feminino",
    "inviteCodeUsed": "6247C5",
    "emailVerified": true
  },
  {
    "date": "2026-01-05 18:22:30",
    "referenceCode": "F37F2E",
    "email": "unhtg46tm2@airsworld.net",
    "username": "CoolHero67",
    "password": "sl#aIz!hK57J",
    "age": 27,
    "gender": "feminino",
    "inviteCodeUsed": "6247C5",
    "emailVerified": true
  },
  {
    "date": "2026-01-05 18:22:47",
    "referenceCode": "BC6D5B",
    "email": "h742fkwoqy@airsworld.net",
    "username": "MegaQueen13",
    "password": "paef63vng6vo",
    "age": 21,
    "gender": "feminino",
    "inviteCodeUsed": "6247C5",
    "emailVerified": true
  },
  {
    "date": "2026-01-05 18:23:04",
    "referenceCode": "38CD4C",
    "email": "6vyexxuyvl@airsworld.net",
    "username": "CoolStar061",
    "password": "l5EZ@JEF67j$",
    "age": 33,
    "gender": "feminino",
    "inviteCodeUsed": "6247C5",
    "emailVerified": true
  },
  {
    "date": "2026-01-05 18:23:22",
    "referenceCode": "FD0795",
    "email": "ibzq9fkjun@airsworld.net",
    "username": "StarLord3529",
    "password": "pmvZzDRGvAui",
    "age": 23,
    "gender": "feminino",
    "inviteCodeUsed": "6247C5",
    "emailVerified": true
  },
  {
    "date": "2026-01-05 18:23:39",
    "referenceCode": "CCEED5",
    "email": "1pqjwrj85q@airsworld.net",
    "username": "CoolQueen5819",
    "password": "x1F@vz$pQrIh",
    "age": 18,
    "gender": "feminino",
    "inviteCodeUsed": "6247C5",
    "emailVerified": true
  },
  {
    "date": "2026-01-05 18:23:56",
    "referenceCode": "2656E3",
    "email": "evg4ki8qmh@airsworld.net",
    "username": "StarPro66",
    "password": "FuKjUR6g%av!",
    "age": 39,
    "gender": "feminino",
    "inviteCodeUsed": "6247C5",
    "emailVerified": true
  },
  {
    "date": "2026-01-05 18:24:12",
    "referenceCode": "0DA14D",
    "email": "b6q7kmia5u@airsworld.net",
    "username": "SuperPlayer525",
    "password": "XiHFJnGYpcQv",
    "age": 39,
    "gender": "masculino",
    "inviteCodeUsed": "6247C5",
    "emailVerified": true
  },
  {
    "date": "2026-01-05 18:24:29",
    "referenceCode": "456497",
    "email": "8at5eti5bx@airsworld.net",
    "username": "MegaGamer582",
    "password": "PM7SuiXIBzEX",
    "age": 18,
    "gender": "masculino",
    "inviteCodeUsed": "6247C5",
    "emailVerified": true
  },
  {
    "date": "2026-01-05 18:24:46",
    "referenceCode": "71EE3C",
    "email": "y2dqkac2sq@airsworld.net",
    "username": "ProLord378",
    "password": "q%Kr2rXPpzhJ",
    "age": 29,
    "gender": "masculino",
    "inviteCodeUsed": "6247C5",
    "emailVerified": true
  },
  {
    "date": "2026-01-05 18:25:03",
    "referenceCode": "7CD49F",
    "email": "6f0mza8dy7@airsworld.net",
    "username": "NovaGamer2062",
    "password": "jZUTjf2IZ04@",
    "age": 23,
    "gender": "feminino",
    "inviteCodeUsed": "6247C5",
    "emailVerified": true
  },
  {
    "date": "2026-01-05 18:25:20",
    "referenceCode": "5DA8FA",
    "email": "lq4hgp3d3e@airsworld.net",
    "username": "StarMaster82",
    "password": "nZqhMA3rWGXt",
    "age": 34,
    "gender": "feminino",
    "inviteCodeUsed": "6247C5",
    "emailVerified": true
  },
  {
    "date": "2026-01-05 18:25:37",
    "referenceCode": "8B0D5E",
    "email": "arrgo4dz4b@airsworld.net",
    "username": "StarHero27",
    "password": "vd9l5l%8$UjI",
    "age": 35,
    "gender": "feminino",
    "inviteCodeUsed": "6247C5",
    "emailVerified": true
  },
  {
    "date": "2026-01-05 18:25:54",
    "referenceCode": "CC2A98",
    "email": "0hxi1dv3v4@airsworld.net",
    "username": "UltraStar848",
    "password": "5u$xXKCkWzE2",
    "age": 22,
    "gender": "masculino",
    "inviteCodeUsed": "6247C5",
    "emailVerified": true
  },
  {
    "date": "2026-01-05 18:26:11",
    "referenceCode": "CC1709",
    "email": "6et0hdj365@airsworld.net",
    "username": "CoolLord217",
    "password": "dOdyBBq0V8Uj",
    "age": 33,
    "gender": "masculino",
    "inviteCodeUsed": "6247C5",
    "emailVerified": true
  },
  {
    "date": "2026-01-05 18:26:28",
    "referenceCode": "58D128",
    "email": "ds3wk1ea1a@airsworld.net",
    "username": "CoolPlayer3007",
    "password": "VV%kcfokuCPN",
    "age": 39,
    "gender": "feminino",
    "inviteCodeUsed": "6247C5",
    "emailVerified": true
  },
  {
    "date": "2026-01-05 18:26:51",
    "referenceCode": "6B2C5C",
    "email": "yrbhhgel@guerrillamailblock.com",
    "username": "PlayPro0008",
    "password": "fnjiNK6r@aKR",
    "age": 36,
    "gender": "feminino",
    "inviteCodeUsed": "6247C5",
    "emailVerified": true
  },
  {
    "date": "2026-01-05 18:27:09",
    "referenceCode": "32D6C5",
    "email": "v2jnozsyzv@airsworld.net",
    "username": "NovaMaster40",
    "password": "3KwKUfQcn9Sq",
    "age": 37,
    "gender": "masculino",
    "inviteCodeUsed": "6247C5",
    "emailVerified": true
  },
  {
    "date": "2026-01-05 18:27:26",
    "referenceCode": "E62145",
    "email": "ot077ze6yn@airsworld.net",
    "username": "NovaQueen3588",
    "password": "miXm2I#XS4GA",
    "age": 19,
    "gender": "feminino",
    "inviteCodeUsed": "6247C5",
    "emailVerified": true
  },
  {
    "date": "2026-01-05 18:27:43",
    "referenceCode": "667F6F",
    "email": "72nztleps4@airsworld.net",
    "username": "SuperLegend64",
    "password": "n@Jyi@eOFQ!S",
    "age": 19,
    "gender": "feminino",
    "inviteCodeUsed": "6247C5",
    "emailVerified": true
  },
  {
    "date": "2026-01-05 18:28:02",
    "referenceCode": "9B61CA",
    "email": "i43byna7wt@airsworld.net",
    "username": "MegaPro384",
    "password": "koZK!D@fIIWJ",
    "age": 40,
    "gender": "feminino",
    "inviteCodeUsed": "6247C5",
    "emailVerified": true
  },
  {
    "date": "2026-01-05 18:28:20",
    "referenceCode": "11C358",
    "email": "t3iosoti8q@airsworld.net",
    "username": "SuperQueen118",
    "password": "$WlK8JS%LRB$",
    "age": 19,
    "gender": "masculino",
    "inviteCodeUsed": "6247C5",
    "emailVerified": true
  },
  {
    "date": "2026-01-05 18:28:37",
    "referenceCode": "302FFB",
    "email": "ht4spcz8jh@airsworld.net",
    "username": "GameKing50",
    "password": "DiqV5iVAG4Iy",
    "age": 23,
    "gender": "feminino",
    "inviteCodeUsed": "6247C5",
    "emailVerified": true
  },
  {
    "date": "2026-01-05 18:28:59",
    "referenceCode": "B51971",
    "email": "n9rin8cvuz@airsworld.net",
    "username": "MegaGamer97",
    "password": "#upgKJcW8JTE",
    "age": 39,
    "gender": "feminino",
    "inviteCodeUsed": "6247C5",
    "emailVerified": true
  },
  {
    "date": "2026-01-05 18:29:15",
    "referenceCode": "22E674",
    "email": "jw4wgzumri@airsworld.net",
    "username": "GameKing88",
    "password": "h61rjj1RI3I0",
    "age": 37,
    "gender": "masculino",
    "inviteCodeUsed": "6247C5",
    "emailVerified": true
  },
  {
    "date": "2026-01-05 18:29:32",
    "referenceCode": "5202F6",
    "email": "y4pt5e63ls@airsworld.net",
    "username": "SuperPro18",
    "password": "ZfDjJQFIbzDD",
    "age": 34,
    "gender": "masculino",
    "inviteCodeUsed": "6247C5",
    "emailVerified": true
  },
  {
    "date": "2026-01-05 18:29:49",
    "referenceCode": "7028EB",
    "email": "3w04gjxegv@airsworld.net",
    "username": "PlayGamer48",
    "password": "4m@w9#IRsCiq",
    "age": 36,
    "gender": "feminino",
    "inviteCodeUsed": "6247C5",
    "emailVerified": true
  },
  {
    "date": "2026-01-05 18:30:06",
    "referenceCode": "13FC86",
    "email": "c8c8dsaho0@airsworld.net",
    "username": "CoolLegend237",
    "password": "Izil3rJSo9l1",
    "age": 32,
    "gender": "feminino",
    "inviteCodeUsed": "6247C5",
    "emailVerified": true
  },
  {
    "date": "2026-01-05 18:30:24",
    "referenceCode": "86489B",
    "email": "65x6j0zuvt@airsworld.net",
    "username": "SuperStar4372",
    "password": "PZ3xfY7OXIvY",
    "age": 31,
    "gender": "masculino",
    "inviteCodeUsed": "6247C5",
    "emailVerified": true
  },
  {
    "date": "2026-01-05 18:30:40",
    "referenceCode": "C8DDB8",
    "email": "jed8pg69bi@airsworld.net",
    "username": "NovaQueen0695",
    "password": "IU!D4@@sK%Iy",
    "age": 42,
    "gender": "feminino",
    "inviteCodeUsed": "6247C5",
    "emailVerified": true
  },
  {
    "date": "2026-01-05 18:30:57",
    "referenceCode": "30E025",
    "email": "s6ktwzk4uk@airsworld.net",
    "username": "ProQueen482",
    "password": "Owyav8GNxB%r",
    "age": 26,
    "gender": "masculino",
    "inviteCodeUsed": "6247C5",
    "emailVerified": true
  },
  {
    "date": "2026-01-05 18:31:14",
    "referenceCode": "FA3ACB",
    "email": "4m2ob0ipka@airsworld.net",
    "username": "PlayPlayer0215",
    "password": "9$as#5FY4deH",
    "age": 35,
    "gender": "masculino",
    "inviteCodeUsed": "6247C5",
    "emailVerified": true
  },
  {
    "date": "2026-01-05 18:31:30",
    "referenceCode": "9E9EEA",
    "email": "3lnue7mita@airsworld.net",
    "username": "ProLord23",
    "password": "61e6HMhmwU6a",
    "age": 26,
    "gender": "feminino",
    "inviteCodeUsed": "6247C5",
    "emailVerified": true
  },
  {
    "date": "2026-01-05 18:31:48",
    "referenceCode": "54E28D",
    "email": "1jotrhrncl@airsworld.net",
    "username": "UltraLegend11",
    "password": "aZ68ddaMc7E4",
    "age": 29,
    "gender": "masculino",
    "inviteCodeUsed": "6247C5",
    "emailVerified": true
  },
  {
    "date": "2026-01-05 18:32:06",
    "referenceCode": "A0766A",
    "email": "qhwyppvlis@airsworld.net",
    "username": "CoolLegend2536",
    "password": "gX8VjA89tgjM",
    "age": 43,
    "gender": "feminino",
    "inviteCodeUsed": "6247C5",
    "emailVerified": true
  },
  {
    "date": "2026-01-05 18:32:22",
    "referenceCode": "E7430D",
    "email": "02esd6ncyc@airsworld.net",
    "username": "GameQueen7306",
    "password": "FJW672#34vIJ",
    "age": 41,
    "gender": "feminino",
    "inviteCodeUsed": "6247C5",
    "emailVerified": true
  },
  {
    "date": "2026-01-05 18:32:51",
    "referenceCode": "2CC040",
    "email": "rdoq0op6sl@airsworld.net",
    "username": "NovaKing943",
    "password": "kKBd9hNOWy!@",
    "age": 43,
    "gender": "masculino",
    "inviteCodeUsed": "6247C5",
    "emailVerified": true
  },
  {
    "date": "2026-01-05 18:33:12",
    "referenceCode": "D380BC",
    "email": "zrcqspr0cg@airsworld.net",
    "username": "UltraKing19",
    "password": "CFJNSTAV3B#d",
    "age": 37,
    "gender": "feminino",
    "inviteCodeUsed": "6247C5",
    "emailVerified": true
  },
  {
    "date": "2026-01-05 18:33:29",
    "referenceCode": "0DAA14",
    "email": "n2ecp5wsd8@airsworld.net",
    "username": "StarKing3902",
    "password": "9qD#Blu7gAbJ",
    "age": 22,
    "gender": "feminino",
    "inviteCodeUsed": "6247C5",
    "emailVerified": true
  },
  {
    "date": "2026-01-05 18:33:52",
    "referenceCode": "C7EF4D",
    "email": "uovk35wdiq@airsworld.net",
    "username": "PlayLegend7445",
    "password": "v$!prdeftMYk",
    "age": 26,
    "gender": "masculino",
    "inviteCodeUsed": "6247C5",
    "emailVerified": true
  },
  {
    "date": "2026-01-05 18:34:08",
    "referenceCode": "2BD7BB",
    "email": "abho47c4tx@airsworld.net",
    "username": "ProKing903",
    "password": "G1B4Ti9$VJ5L",
    "age": 42,
    "gender": "masculino",
    "inviteCodeUsed": "6247C5",
    "emailVerified": true
  },
  {
    "date": "2026-01-05 18:34:25",
    "referenceCode": "59ED4A",
    "email": "6id7m7amse@airsworld.net",
    "username": "CoolKing8541",
    "password": "CY!P@gWlWvOy",
    "age": 40,
    "gender": "feminino",
    "inviteCodeUsed": "6247C5",
    "emailVerified": true
  },
  {
    "date": "2026-01-05 18:34:42",
    "referenceCode": "9A3188",
    "email": "l9tyb62s54@airsworld.net",
    "username": "PlayKing938",
    "password": "OglQisJdqngP",
    "age": 30,
    "gender": "feminino",
    "inviteCodeUsed": "6247C5",
    "emailVerified": true
  },
  {
    "date": "2026-01-05 18:35:05",
    "referenceCode": "7F9704",
    "email": "h2vkoe7x37@airsworld.net",
    "username": "StarMaster74",
    "password": "$j@mLsnqGiT3",
    "age": 40,
    "gender": "feminino",
    "inviteCodeUsed": "6247C5",
    "emailVerified": true
  },
  {
    "date": "2026-01-05 18:35:28",
    "referenceCode": "75B232",
    "email": "m92da1klbq@airsworld.net",
    "username": "GamePro26",
    "password": "pMsP5%v6fs53",
    "age": 18,
    "gender": "feminino",
    "inviteCodeUsed": "6247C5",
    "emailVerified": true
  },
  {
    "date": "2026-01-05 18:35:45",
    "referenceCode": "2CB34F",
    "email": "xtexpb3ufl@airsworld.net",
    "username": "PlayHero8918",
    "password": "n4$bB0$HO9$o",
    "age": 44,
    "gender": "feminino",
    "inviteCodeUsed": "6247C5",
    "emailVerified": true
  },
  {
    "date": "2026-01-05 18:36:02",
    "referenceCode": "84F322",
    "email": "05pts04vd8@airsworld.net",
    "username": "EpicMaster7389",
    "password": "TCdYEUB4jANd",
    "age": 22,
    "gender": "feminino",
    "inviteCodeUsed": "6247C5",
    "emailVerified": true
  },
  {
    "date": "2026-01-05 18:36:24",
    "referenceCode": "15A598",
    "email": "uwoe903dze@airsworld.net",
    "username": "CoolLegend1421",
    "password": "NqPFLv#6%HF@",
    "age": 30,
    "gender": "feminino",
    "inviteCodeUsed": "6247C5",
    "emailVerified": true
  },
  {
    "date": "2026-01-05 18:36:41",
    "referenceCode": "368932",
    "email": "zw3dmt2zsw@airsworld.net",
    "username": "UltraLord45",
    "password": "SRhKoRHeyQKd",
    "age": 21,
    "gender": "feminino",
    "inviteCodeUsed": "6247C5",
    "emailVerified": true
  },
  {
    "date": "2026-01-05 18:36:58",
    "referenceCode": "AC4419",
    "email": "xnj334kioi@airsworld.net",
    "username": "NovaLegend148",
    "password": "rxI5ms1TL4Zz",
    "age": 23,
    "gender": "masculino",
    "inviteCodeUsed": "6247C5",
    "emailVerified": true
  },
  {
    "date": "2026-01-05 18:37:15",
    "referenceCode": "5DBC92",
    "email": "rouml9es1q@airsworld.net",
    "username": "EpicLord98",
    "password": "Q8$$wEG8ypYv",
    "age": 40,
    "gender": "masculino",
    "inviteCodeUsed": "6247C5",
    "emailVerified": true
  },
  {
    "date": "2026-01-05 18:37:32",
    "referenceCode": "1F24AC",
    "email": "zevuylxb9c@airsworld.net",
    "username": "EpicLord32",
    "password": "8DExOnciu1gG",
    "age": 45,
    "gender": "feminino",
    "inviteCodeUsed": "6247C5",
    "emailVerified": true
  },
  {
    "date": "2026-01-05 18:37:49",
    "referenceCode": "0C41C9",
    "email": "7pvmalkfcr@airsworld.net",
    "username": "PlayPlayer260",
    "password": "3hBgWAH3Bo#v",
    "age": 37,
    "gender": "feminino",
    "inviteCodeUsed": "6247C5",
    "emailVerified": true
  },
  {
    "date": "2026-01-05 18:38:05",
    "referenceCode": "335C6D",
    "email": "skc26phsle@airsworld.net",
    "username": "StarPlayer74",
    "password": "QOePv$6FHmC1",
    "age": 31,
    "gender": "masculino",
    "inviteCodeUsed": "6247C5",
    "emailVerified": true
  },
  {
    "date": "2026-01-05 18:38:22",
    "referenceCode": "24B6BC",
    "email": "op1p0qp6ml@airsworld.net",
    "username": "NovaQueen7487",
    "password": "0Xq0Ve#KAq$r",
    "age": 24,
    "gender": "masculino",
    "inviteCodeUsed": "6247C5",
    "emailVerified": true
  },
  {
    "date": "2026-01-05 18:38:38",
    "referenceCode": "41C73D",
    "email": "ckfy277y29@airsworld.net",
    "username": "StarQueen15",
    "password": "fX6T%QXz1%d5",
    "age": 20,
    "gender": "masculino",
    "inviteCodeUsed": "6247C5",
    "emailVerified": true
  },
  {
    "date": "2026-01-05 18:38:55",
    "referenceCode": "01EF3B",
    "email": "uow7d2f1il@airsworld.net",
    "username": "PlayQueen1378",
    "password": "godS2eeqvGQ8",
    "age": 45,
    "gender": "masculino",
    "inviteCodeUsed": "6247C5",
    "emailVerified": true
  },
  {
    "date": "2026-01-05 18:39:14",
    "referenceCode": "387211",
    "email": "nx23nh2cf7@airsworld.net",
    "username": "NovaHero975",
    "password": "Ms9fuzQC7PUT",
    "age": 33,
    "gender": "masculino",
    "inviteCodeUsed": "6247C5",
    "emailVerified": true
  },
  {
    "date": "2026-01-05 18:39:30",
    "referenceCode": "5D9FF9",
    "email": "uaet6c1sjh@airsworld.net",
    "username": "NovaKing442",
    "password": "3ntomY0ZpXuU",
    "age": 37,
    "gender": "feminino",
    "inviteCodeUsed": "6247C5",
    "emailVerified": true
  },
  {
    "date": "2026-01-05 18:39:47",
    "referenceCode": "B24253",
    "email": "6li8m0cf15@airsworld.net",
    "username": "SuperQueen73",
    "password": "V1O9KS5AlCOT",
    "age": 24,
    "gender": "masculino",
    "inviteCodeUsed": "6247C5",
    "emailVerified": true
  },
  {
    "date": "2026-01-05 18:40:04",
    "referenceCode": "194809",
    "email": "wz1rnulp12@airsworld.net",
    "username": "EpicLegend51",
    "password": "oHS0SZSfDcJH",
    "age": 23,
    "gender": "masculino",
    "inviteCodeUsed": "6247C5",
    "emailVerified": true
  },
  {
    "date": "2026-01-05 18:40:21",
    "referenceCode": "8BDF96",
    "email": "c7hj0xjbf6@airsworld.net",
    "username": "SuperQueen6017",
    "password": "hOhKdiYrlDiT",
    "age": 28,
    "gender": "feminino",
    "inviteCodeUsed": "6247C5",
    "emailVerified": true
  },
  {
    "date": "2026-01-05 18:40:37",
    "referenceCode": "D03788",
    "email": "zbr3sqbs9q@airsworld.net",
    "username": "MegaGamer4791",
    "password": "@6UouYJkW5$g",
    "age": 40,
    "gender": "feminino",
    "inviteCodeUsed": "6247C5",
    "emailVerified": true
  },
  {
    "date": "2026-01-05 18:40:54",
    "referenceCode": "8B6AAB",
    "email": "5y2ldhfvi8@airsworld.net",
    "username": "PlayKing6822",
    "password": "mEjdFBQEbm7%",
    "age": 33,
    "gender": "feminino",
    "inviteCodeUsed": "6247C5",
    "emailVerified": true
  },
  {
    "date": "2026-01-05 18:41:11",
    "referenceCode": "7AF89C",
    "email": "rotxfullex@airsworld.net",
    "username": "CoolStar019",
    "password": "bVdDuEmGLJY7",
    "age": 19,
    "gender": "masculino",
    "inviteCodeUsed": "6247C5",
    "emailVerified": true
  },
  {
    "date": "2026-01-05 18:41:29",
    "referenceCode": "1930B6",
    "email": "f1k9hauge8@airsworld.net",
    "username": "StarStar873",
    "password": "a7Mck3Wc0OOb",
    "age": 33,
    "gender": "masculino",
    "inviteCodeUsed": "6247C5",
    "emailVerified": true
  },
  {
    "date": "2026-01-05 18:41:46",
    "referenceCode": "A331A4",
    "email": "lhel08lcpi@airsworld.net",
    "username": "StarKing216",
    "password": "Pc$usYbJZ6Xf",
    "age": 34,
    "gender": "masculino",
    "inviteCodeUsed": "6247C5",
    "emailVerified": true
  },
  {
    "date": "2026-01-05 18:42:03",
    "referenceCode": "E3FC5F",
    "email": "c5zjkd1awg@airsworld.net",
    "username": "MegaKing591",
    "password": "P20GOvPM$t7o",
    "age": 20,
    "gender": "masculino",
    "inviteCodeUsed": "6247C5",
    "emailVerified": true
  },
  {
    "date": "2026-01-05 18:42:20",
    "referenceCode": "18EF11",
    "email": "9fftpb1s2n@airsworld.net",
    "username": "StarQueen622",
    "password": "Ba0JPWm7Ya3I",
    "age": 22,
    "gender": "masculino",
    "inviteCodeUsed": "6247C5",
    "emailVerified": true
  },
  {
    "date": "2026-01-05 18:42:38",
    "referenceCode": "1D69BA",
    "email": "kuy465j5fy@airsworld.net",
    "username": "SuperMaster3724",
    "password": "qN@SjjwGFbu8",
    "age": 44,
    "gender": "masculino",
    "inviteCodeUsed": "6247C5",
    "emailVerified": true
  },
  {
    "date": "2026-01-05 18:42:55",
    "referenceCode": "0FDAB8",
    "email": "2a33mbgb92@airsworld.net",
    "username": "UltraHero938",
    "password": "5nCEIRQ!Cgl#",
    "age": 35,
    "gender": "feminino",
    "inviteCodeUsed": "6247C5",
    "emailVerified": true
  },
  {
    "date": "2026-01-05 18:43:21",
    "referenceCode": "40A01F",
    "email": "kxrtfsex@guerrillamailblock.com",
    "username": "GameGamer88",
    "password": "qBWz##uxsfdL",
    "age": 40,
    "gender": "masculino",
    "inviteCodeUsed": "6247C5",
    "emailVerified": true
  },
  {
    "date": "2026-01-05 18:43:39",
    "referenceCode": "9C101F",
    "email": "9da0ci92rv@airsworld.net",
    "username": "ProGamer5349",
    "password": "VeQNYdot$HrP",
    "age": 19,
    "gender": "masculino",
    "inviteCodeUsed": "6247C5",
    "emailVerified": true
  },
  {
    "date": "2026-01-05 18:43:55",
    "referenceCode": "EFA546",
    "email": "61haaopyzy@airsworld.net",
    "username": "StarPlayer619",
    "password": "ONKFV2OU4%XZ",
    "age": 38,
    "gender": "masculino",
    "inviteCodeUsed": "6247C5",
    "emailVerified": true
  },
  {
    "date": "2026-01-05 18:44:12",
    "referenceCode": "3AEA2E",
    "email": "voifhk4hv7@airsworld.net",
    "username": "GameStar33",
    "password": "GHoUJYS$MWy$",
    "age": 34,
    "gender": "feminino",
    "inviteCodeUsed": "6247C5",
    "emailVerified": true
  },
  {
    "date": "2026-01-05 18:44:29",
    "referenceCode": "C45862",
    "email": "06cyp8gg4i@airsworld.net",
    "username": "GameQueen093",
    "password": "ZGpRTgMD8E4n",
    "age": 25,
    "gender": "masculino",
    "inviteCodeUsed": "6247C5",
    "emailVerified": true
  },
  {
    "date": "2026-01-05 18:44:52",
    "referenceCode": "A6DBF2",
    "email": "rfuxtyov@guerrillamailblock.com",
    "username": "MegaMaster328",
    "password": "xp3vd3iUF9Hg",
    "age": 28,
    "gender": "masculino",
    "inviteCodeUsed": "6247C5",
    "emailVerified": true
  },
  {
    "date": "2026-01-05 18:45:09",
    "referenceCode": "BE3188",
    "email": "w1snbhib04@airsworld.net",
    "username": "CoolGamer8689",
    "password": "Lpd%Fp0S5G#j",
    "age": 24,
    "gender": "feminino",
    "inviteCodeUsed": "6247C5",
    "emailVerified": true
  },
  {
    "date": "2026-01-05 18:45:26",
    "referenceCode": "95ECD0",
    "email": "nn9tbud1cn@airsworld.net",
    "username": "ProMaster299",
    "password": "!y%KRk5HYuSM",
    "age": 44,
    "gender": "feminino",
    "inviteCodeUsed": "6247C5",
    "emailVerified": true
  },
  {
    "date": "2026-01-05 18:45:43",
    "referenceCode": "C87E7F",
    "email": "s9829vvgha@airsworld.net",
    "username": "PlayLord656",
    "password": "uYHwYoWFUF%L",
    "age": 38,
    "gender": "feminino",
    "inviteCodeUsed": "6247C5",
    "emailVerified": true
  },
  {
    "date": "2026-01-05 18:46:01",
    "referenceCode": "09D6EA",
    "email": "ztoaxun8xi@airsworld.net",
    "username": "NovaHero74",
    "password": "8oe5RFotjjll",
    "age": 18,
    "gender": "masculino",
    "inviteCodeUsed": "6247C5",
    "emailVerified": true
  },
  {
    "date": "2026-01-05 18:46:18",
    "referenceCode": "487E1F",
    "email": "lyvehlsog0@airsworld.net",
    "username": "MegaQueen3570",
    "password": "DQcVIGWdcIIf",
    "age": 20,
    "gender": "feminino",
    "inviteCodeUsed": "6247C5",
    "emailVerified": true
  },
  {
    "date": "2026-01-05 18:46:35",
    "referenceCode": "EB6DF6",
    "email": "n72e7nnz0f@airsworld.net",
    "username": "StarLegend19",
    "password": "a2QXG0idpsFz",
    "age": 30,
    "gender": "feminino",
    "inviteCodeUsed": "6247C5",
    "emailVerified": true
  },
  {
    "date": "2026-01-05 18:46:52",
    "referenceCode": "2D7A20",
    "email": "gtsn4149ue@airsworld.net",
    "username": "UltraLord12",
    "password": "uLHU5MmWh9bx",
    "age": 44,
    "gender": "feminino",
    "inviteCodeUsed": "6247C5",
    "emailVerified": true
  },
  {
    "date": "2026-01-05 18:47:08",
    "referenceCode": "01D857",
    "email": "png8er0dil@airsworld.net",
    "username": "CoolHero4648",
    "password": "Tntllrnz69ta",
    "age": 39,
    "gender": "feminino",
    "inviteCodeUsed": "6247C5",
    "emailVerified": true
  },
  {
    "date": "2026-01-05 18:47:25",
    "referenceCode": "4B8E31",
    "email": "dto5pw864u@airsworld.net",
    "username": "GameHero939",
    "password": "E#feCw!Qk%%E",
    "age": 22,
    "gender": "feminino",
    "inviteCodeUsed": "6247C5",
    "emailVerified": true
  },
  {
    "date": "2026-01-05 18:47:41",
    "referenceCode": "6BCB18",
    "email": "wrg6rq9e8e@airsworld.net",
    "username": "GamePro07",
    "password": "DaifP1C3%#@Y",
    "age": 35,
    "gender": "masculino",
    "inviteCodeUsed": "6247C5",
    "emailVerified": true
  },
  {
    "date": "2026-01-05 18:47:58",
    "referenceCode": "822746",
    "email": "ionug5qdgb@airsworld.net",
    "username": "SuperStar6633",
    "password": "F1TOZdOH9x8@",
    "age": 27,
    "gender": "feminino",
    "inviteCodeUsed": "6247C5",
    "emailVerified": true
  },
  {
    "date": "2026-01-05 18:48:15",
    "referenceCode": "75DDF7",
    "email": "jjec0g7xhn@airsworld.net",
    "username": "StarPlayer9191",
    "password": "J9axkof5bIKM",
    "age": 44,
    "gender": "feminino",
    "inviteCodeUsed": "6247C5",
    "emailVerified": true
  },
  {
    "date": "2026-01-05 18:48:33",
    "referenceCode": "20B73A",
    "email": "w4usi9zyxq@airsworld.net",
    "username": "UltraPlayer1799",
    "password": "@VjJaVbQTbi7",
    "age": 28,
    "gender": "feminino",
    "inviteCodeUsed": "6247C5",
    "emailVerified": true
  },
  {
    "date": "2026-01-05 18:48:51",
    "referenceCode": "F68F54",
    "email": "pu8s9vzodh@airsworld.net",
    "username": "StarHero828",
    "password": "azaoEaVoJ3Z!",
    "age": 23,
    "gender": "masculino",
    "inviteCodeUsed": "6247C5",
    "emailVerified": true
  },
  {
    "date": "2026-01-05 18:49:08",
    "referenceCode": "88A1CA",
    "email": "26nr6nxtjf@airsworld.net",
    "username": "EpicKing212",
    "password": "m0P8g9KAQeTD",
    "age": 31,
    "gender": "feminino",
    "inviteCodeUsed": "6247C5",
    "emailVerified": true
  },
  {
    "date": "2026-01-05 18:49:24",
    "referenceCode": "EF481D",
    "email": "kgbycb3mh3@airsworld.net",
    "username": "GameKing54",
    "password": "n#yKwGPD4#Fg",
    "age": 26,
    "gender": "masculino",
    "inviteCodeUsed": "6247C5",
    "emailVerified": true
  },
  {
    "date": "2026-01-05 18:49:42",
    "referenceCode": "576F6B",
    "email": "8kwgwiu3ux@airsworld.net",
    "username": "EpicPro53",
    "password": "XWmpdsdvh@ha",
    "age": 27,
    "gender": "masculino",
    "inviteCodeUsed": "6247C5",
    "emailVerified": true
  },
  {
    "date": "2026-01-05 18:50:05",
    "referenceCode": "2ADE73",
    "email": "1lk1p82fd6@airsworld.net",
    "username": "NovaQueen0074",
    "password": "Su8X1QP%@Pci",
    "age": 31,
    "gender": "feminino",
    "inviteCodeUsed": "6247C5",
    "emailVerified": true
  },
  {
    "date": "2026-01-05 18:50:22",
    "referenceCode": "6149DA",
    "email": "moh3c4sln3@airsworld.net",
    "username": "StarLegend309",
    "password": "wsVsn!2yPvSj",
    "age": 44,
    "gender": "feminino",
    "inviteCodeUsed": "6247C5",
    "emailVerified": true
  }
]